cglbtrial5_nc/__init__.py
cglbtrial5_nc/file_reader_csv.py
cglbtrial5_nc/plugin.py
cglbtrial5_nc-0.5.0.dist-info/METADATA
cglbtrial5_nc-0.5.0.dist-info/WHEEL
cglbtrial5_nc-0.5.0.dist-info/entry_points.txt
cglbtrial5_nc-0.5.0.dist-info/RECORD
