Metadata-Version: 2.1
Name: cglbtrial5-nc
Version: 0.5.0
Summary: cglbtrial5-nc is cglbtrial5-nc
Home-page: https://cesgenslab.cloud/
Author: CesGensLaB
Author-email: contact@cesgenlab.fr
Requires-Python: >=3.11,<4.0
Classifier: Programming Language :: Python :: 3
Classifier: Programming Language :: Python :: 3.11
Classifier: Programming Language :: Python :: 3.12
Requires-Dist: cglbtrial5 (>=0.4.0)
